dbusnotify/__init__.py
dbusnotify-0.0.2.dist-info/DESCRIPTION.rst
dbusnotify-0.0.2.dist-info/METADATA
dbusnotify-0.0.2.dist-info/RECORD
dbusnotify-0.0.2.dist-info/WHEEL
dbusnotify-0.0.2.dist-info/metadata.json
dbusnotify-0.0.2.dist-info/top_level.txt
