Metadata-Version: 2.0
Name: dbusnotify
Version: 0.0.2
Summary: dbusnotify is a library for creating desktop notifications using the freedesktop.org notification spec
Home-page: https://github.com/frostidaho/python-dbusnotify
Author: Frost Idaho
Author-email: frostidaho@gmail.com
License: BSD
Download-URL: https://github.com/frostidaho/python-dbusnotify/tarball/0.0.2
Platform: UNKNOWN
Classifier: Development Status :: 3 - Alpha
Classifier: Intended Audience :: Developers
Classifier: Programming Language :: Python :: 3
